{
  "EytLgZytPSwzMizHbyC2Y8Et1wwqriywWoouvgfHpump": {
    "mint": "EytLgZytPSwzMizHbyC2Y8Et1wwqriywWoouvgfHpump",
    "totalAmount": 0,
    "averagePrice": 0.000005429286620560965,
    "averagePriceUSD": 0.0009485871613845541,
    "totalInvested": 0.05146,
    "totalInvestedUSD": 8.99092251641074,
    "transactions": [
      {
        "signature": "3mfuCjaNnPj8CH24BdZd5Q3hMj6TUsK7vAWkiM1fkYy2B2ZiJ8orqxrco5BVz8Br1UoHu4mWWisn3TwQwjuhjH8c",
        "type": "BUY",
        "amount": 9478.224967,
        "price": 0.000005429286620560965,
        "priceUSD": 0.0009485871613845541,
        "solAmount": 0.05146,
        "usdAmount": 8.99092251641074,
        "solPriceAtTime": 174.71672204451494,
        "timestamp": "2025-05-27T16:27:11.627Z"
      },
      {
        "signature": "3Um79vSXNkf1bj1bKG88kob9g18kouSGswFc67s6nBK3wGjwLEuCBGDxzbNeHCBANtSY4JwXvLZJCckGsEYwJq8F",
        "type": "SELL",
        "amount": 9478.224967,
        "price": 0.000007868553474902975,
        "priceUSD": 0.0013747678703670252,
        "solAmount": 0.07457992,
        "usdAmount": 13.03035915274216,
        "solPriceAtTime": 174.71672204451494,
        "timestamp": "2025-05-27T16:39:21.966Z"
      }
    ],
    "status": "CLOSED",
    "openedAt": "2025-05-27T16:27:11.627Z",
    "lastUpdate": "2025-05-27T16:27:11.627Z",
    "closedAt": "2025-05-27T16:39:21.966Z",
    "finalPnL": 0.023119919999999995,
    "finalPnLUSD": 4.03943663633142
  },
  "6KTefwGvQ4wgmNeobuzhTCKKE55vFoj5dJryAMp8Hau6": {
    "mint": "6KTefwGvQ4wgmNeobuzhTCKKE55vFoj5dJryAMp8Hau6",
    "totalAmount": 2524107.181848918,
    "averagePrice": 1.2402405185135193e-8,
    "averagePriceUSD": 0.0000021669075794147162,
    "totalInvested": 0.031305,
    "totalInvestedUSD": 5.46950698360354,
    "transactions": [
      {
        "signature": "2Wm6Uc1wUG6TKHZtffo3QQdudD6P1TMpgjUHzHzb9A5VbqtE2HzBsNsqHQAeVgCWRsKgFEkrJroitcpu9sT2KpbN",
        "type": "BUY",
        "amount": 2524107.181848918,
        "price": 1.2402405185135193e-8,
        "priceUSD": 0.0000021669075794147162,
        "solAmount": 0.031305,
        "usdAmount": 5.46950698360354,
        "solPriceAtTime": 174.71672204451494,
        "timestamp": "2025-05-27T16:33:22.337Z"
      }
    ],
    "status": "OPEN",
    "openedAt": "2025-05-27T16:33:22.337Z",
    "lastUpdate": "2025-05-27T16:33:22.337Z"
  }
}